myosdk/__init__.py
myosdk/assets.py
myosdk/characters.py
myosdk/client.py
myosdk/exceptions.py
myosdk/http.py
myosdk/jobs.py
myosdk-0.1.0.dist-info/METADATA
myosdk-0.1.0.dist-info/WHEEL
myosdk-0.1.0.dist-info/RECORD
