Metadata-Version: 2.4
Name: myosdk
Version: 0.1.0
Summary: Python SDK for MyoSapiens API
Requires-Python: >=3.10
Requires-Dist: httpx>=0.28.1
Provides-Extra: dev
Requires-Dist: pytest-asyncio>=0.21.0; extra == 'dev'
Requires-Dist: pytest-mock>=3.12.0; extra == 'dev'
Requires-Dist: pytest>=7.4.0; extra == 'dev'
